TDMtermite.cp37-win_amd64.pyd
TDMtermite-2.1.2.dist-info/LICENSE
TDMtermite-2.1.2.dist-info/METADATA
TDMtermite-2.1.2.dist-info/WHEEL
TDMtermite-2.1.2.dist-info/top_level.txt
TDMtermite-2.1.2.dist-info/RECORD
