Metadata-Version: 2.2
Name: TDMtermite
Version: 2.1.2
Summary: Extract and read data from National Instruments LabVIEW tdx/tdm files and export them as csv files
Home-page: https://github.com/RecordEvolution/TDMtermite.git
Author: Record Evolution GmbH
Author-email: mario.fink@record-evolution.de
Maintainer: Record Evolution GmbH
License: MIT License
Keywords: TDM,TDX,National Instruments,DIAdem,LabVIEW,Measurement Studio,SignalExpress
Classifier: Programming Language :: Python :: 3
Classifier: License :: OSI Approved :: MIT License
Classifier: Operating System :: OS Independent
Classifier: Topic :: Scientific/Engineering
Classifier: Topic :: Software Development :: Libraries :: Python Modules
License-File: LICENSE
